nav_online_szamla/__init__.py
nav_online_szamla/client.py
nav_online_szamla/config.py
nav_online_szamla/excel/__init__.py
nav_online_szamla/excel/exceptions.py
nav_online_szamla/excel/exporter.py
nav_online_szamla/excel/importer.py
nav_online_szamla/excel/mapper.py
nav_online_szamla/excel/models.py
nav_online_szamla/excel/streaming_exporter.py
nav_online_szamla/excel/transaction_exporter.py
nav_online_szamla/excel/transaction_mapper.py
nav_online_szamla/excel_mapper.py
nav_online_szamla/exceptions.py
nav_online_szamla/file_storage.py
nav_online_szamla/http_client.py
nav_online_szamla/models/__init__.py
nav_online_szamla/models/catalog.py
nav_online_szamla/models/common.py
nav_online_szamla/models/invoice_annulment.py
nav_online_szamla/models/invoice_api.py
nav_online_szamla/models/invoice_base.py
nav_online_szamla/models/invoice_data.py
nav_online_szamla/models/service_metrics.py
nav_online_szamla/models_legacy.py
nav_online_szamla/utils.py
nav_online_szamla-0.0.34.dist-info/WHEEL
nav_online_szamla-0.0.34.dist-info/METADATA
nav_online_szamla-0.0.34.dist-info/RECORD
