Metadata-Version: 2.3
Name: nav-online-szamla
Version: 0.0.34
Summary: NAV Online Számla
Keywords: nav,online,szamla,hungarian,invoice,tax
Author: Gergo Emmert
Author-email: Gergo Emmert <gergo.emmert@fxltech.com>
Classifier: Development Status :: 3 - Alpha
Classifier: Intended Audience :: Developers
Classifier: License :: OSI Approved :: MIT License
Classifier: Programming Language :: Python :: 3
Classifier: Programming Language :: Python :: 3.9
Classifier: Programming Language :: Python :: 3.10
Classifier: Programming Language :: Python :: 3.11
Classifier: Programming Language :: Python :: 3.12
Classifier: Programming Language :: Python :: 3.13
Classifier: Topic :: Office/Business :: Financial :: Accounting
Classifier: Programming Language :: Python :: 3.14
Requires-Dist: requests>=2.31.0,<3
Requires-Dist: pysimplesoap>=1.16.0,<2
Requires-Dist: pandas>=2.1.0,<3
Requires-Dist: openpyxl>=3.1.0,<4
Requires-Dist: dotenv>=0.9.9,<0.10
Requires-Dist: tenacity>=9.0.0,<10
Requires-Dist: xsdata[cli]>=25.7,<26
Requires-Dist: cryptography>=44.0.1,<45
Requires-Dist: xlsxwriter>=3.2.9,<4
Requires-Python: >=3.9, <4.0
Project-URL: Homepage, https://github.com/FXL-Lab/nav-online-szamla
Project-URL: Repository, https://github.com/FXL-Lab/nav-online-szamla
Project-URL: Documentation, https://github.com/FXL-Lab/nav-online-szamla#readme
